tadamz/__init__.py
tadamz/adapt_retention_time.py
tadamz/check_qualifier_peaks.py
tadamz/classify_peaks.py
tadamz/coeluting_peaks.py
tadamz/correct_isotopologue_overlays.py
tadamz/create_random_forest_peak_classifier.py
tadamz/example_workflow.py
tadamz/extract_peaks.py
tadamz/extract_peaks_from_chromatograms.py
tadamz/in_out.py
tadamz/normalize_peaks.py
tadamz/peaks_table.py
tadamz/processing_steps.py
tadamz/quantify.py
tadamz/std_free_normalization.py
tadamz/track_changes.py
tadamz/update_sample_information.py
tadamz/utils.py
tadamz/workflow.py
tadamz/calibration/__init__.py
tadamz/calibration/calibrate.py
tadamz/calibration/calibration_model.py
tadamz/data/default_config.txt
tadamz/data/example_peaks_info_table.xlsx
tadamz/data/srm_peak_classifier.onnx
tadamz/data/srm_peak_classifier.table
tadamz/data/uplc_MS1_QEx_peak_classifier.onnx
tadamz/data/uplc_MS1_QEx_peak_classifier.table
tadamz/emzed_fixes/__init__.py
tadamz/emzed_fixes/_empty_peakmap.py
tadamz/emzed_fixes/fix_integrate_chromatogram_formats.py
tadamz/emzed_fixes/load_peak_map.py
tadamz/emzed_fixes/ms_chromatogram_to_peakmap.py
tadamz/emzed_fixes/optimizations.py
tadamz/emzed_fixes/pick_ms_chromatogram_peaks.py
tadamz/emzed_fixes/subtract_baselines.py
tadamz/emzed_fixes/quantification/__init__.py
tadamz/emzed_fixes/quantification/peak_integration.py
tadamz/emzed_fixes/quantification/peak_shape_models/__init__.py
tadamz/emzed_fixes/quantification/peak_shape_models/asymmetric_gauss_model.py
tadamz/emzed_fixes/quantification/peak_shape_models/base.py
tadamz/emzed_fixes/quantification/peak_shape_models/linear_interpolation_model.py
tadamz/emzed_fixes/quantification/peak_shape_models/no_model.py
tadamz/emzed_fixes/quantification/peak_shape_models/savgol_model.py
tadamz/emzed_fixes/quantification/peak_shape_models/simplified_emg.py
tadamz/scoring/__init__.py
tadamz/scoring/peak_metrics.py
tadamz/scoring/random_forest_peak_classification.py
tadamz-0.13.0a11.dist-info/licenses/LICENSE
tadamz-0.13.0a11.dist-info/METADATA
tadamz-0.13.0a11.dist-info/WHEEL
tadamz-0.13.0a11.dist-info/top_level.txt
tadamz-0.13.0a11.dist-info/RECORD
