Metadata-Version: 2.4
Name: tadamz
Version: 0.13.0a11
Summary: package for targeted LC-MS(/MS) data analysis
Author: Patrick
Author-email: pkiefer@ethz.ch
License: MIT License
Classifier: Intended Audience :: Science/Research
Classifier: Intended Audience :: End Users/Desktop
Classifier: License :: OSI Approved :: MIT License
Classifier: Natural Language :: English
Classifier: Programming Language :: Python :: 3
Classifier: Programming Language :: Python :: 3.9
Classifier: Programming Language :: Python :: 3.10
Classifier: Operating System :: OS Independent
Requires-Python: >=3.10
License-File: LICENSE
Requires-Dist: emzed>=3.0.0
Requires-Dist: pyyaml
Requires-Dist: uncertainties
Requires-Dist: skl2onnx==1.19.1
Requires-Dist: onnx>=1.2.1
Requires-Dist: onnxruntime==1.22.1
Requires-Dist: pybaselines==1.1.0
Dynamic: license-file
